acdh_collatex_utils/__init__.py
acdh_collatex_utils/acdh_collatex_utils.py
acdh_collatex_utils/chunks.py
acdh_collatex_utils/cli.py
acdh_collatex_utils/collatex_patch.py
acdh_collatex_utils/post_process.py
acdh_collatex_utils/xslt/lem.xsl
acdh_collatex_utils/xslt/only_text.xsl
acdh_collatex_utils-1.12.dist-info/LICENSE
acdh_collatex_utils-1.12.dist-info/METADATA
acdh_collatex_utils-1.12.dist-info/WHEEL
acdh_collatex_utils-1.12.dist-info/entry_points.txt
acdh_collatex_utils-1.12.dist-info/top_level.txt
acdh_collatex_utils-1.12.dist-info/RECORD
