Metadata-Version: 2.1
Name: acdh-collatex-utils
Version: 1.12
Summary: Utility functions to work with collatex
Home-page: https://github.com/acdh-oeaw/acdh_collatex_utils
Author: Peter Andorfer
Author-email: peter.andorfer@oeaw.ac.at
License: MIT license
Keywords: acdh_collatex_utils
Classifier: Development Status :: 2 - Pre-Alpha
Classifier: Intended Audience :: Developers
Classifier: License :: OSI Approved :: MIT License
Classifier: Natural Language :: English
Classifier: Programming Language :: Python :: 3.8
Requires-Python: >=3.8
License-File: LICENSE
Requires-Dist: acdh-tei-pyutils (<1,>=0.25.0)
Requires-Dist: beautifulsoup4 (<5,>=4.11.1)
Requires-Dist: click (>=7.1<9)
Requires-Dist: collatex (==2.2)
Requires-Dist: pandas (<2,>=1.1.5)
Requires-Dist: python-Levenshtein
Requires-Dist: tqdm (<5,>=4.52.0)
